[{"Id":644476649,"SocialSecurityNumber":"198805199299","FirstName":"Marco Antonio","LastName":"Villegas Tello","FullName":"Marco Antonio Villegas Tello","Email":"marco.villegas@live.se","Password":"abcd1234","PhoneNumber":null,"MobilePhoneNumber":null,"AgreeMarketing":true,"SubscribeToEmailNotification":true,"ProfileImage":null,"AddressId":2008092754,"Gender":"Man"},{"Id":835089905,"SocialSecurityNumber":"198507119595","FirstName":"Khaled","LastName":"Abo","FullName":"Khaled Abo","Email":"khaledabou1985@gmail.com","Password":"test123","PhoneNumber":null,"MobilePhoneNumber":null,"AgreeMarketing":true,"SubscribeToEmailNotification":true,"ProfileImage":null,"AddressId":391780642,"Gender":"Man"}]